{
  "package": "@planisfy/map-styles",
  "release": "planisfy-streets-v1.0.0",
  "status": "fixture-release",
  "schemaVersion": "planisfy-streets-source-layers-v1",
  "tilesets": [
    {
      "id": "planisfy-streets-v1",
      "name": "Planisfy Streets v1",
      "status": "fixture",
      "format": "pmtiles",
      "tileset": "planisfy.basic",
      "martinSource": "stuttgart-base",
      "sourceLayerContract": "source-layer-contract.json",
      "artifact": {
        "path": "infra/docker/data/pmtiles/stuttgart.pmtiles",
        "requiredForLocalRender": true,
        "mutableLocalFixture": true
      },
      "bounds": [-180, -85.0511, 180, 85.0511],
      "minZoom": 0,
      "maxZoom": 14,
      "dataSources": [
        {
          "name": "Overture Maps",
          "purpose": "Roads, buildings, places, land, water, and admin data for future generated releases.",
          "distribution": "GeoParquet by release/theme/type plus PMTiles inspection artifacts."
        },
        {
          "name": "Natural Earth",
          "purpose": "Low-zoom global land, water, boundaries, and label context.",
          "distribution": "1:10m, 1:50m, and 1:110m vector/raster datasets."
        }
      ],
      "attribution": "© Overture Maps contributors; Natural Earth; OpenStreetMap contributors where applicable"
    }
  ],
  "styles": [
    {
      "id": "planisfy-streets-v1",
      "name": "Planisfy Streets v1",
      "status": "legacy-fixture-alias",
      "style": "styles/planisfy-streets-v1.json",
      "variantOf": "planisfy-streets-light-v1",
      "schema": "schemas/planisfy-streets-v1.schema.json",
      "center": [9.1829, 48.7758],
      "notes": [
        "Backwards-compatible fixture style for local demo wiring."
      ]
    },
    {
      "id": "planisfy-streets-light-v1",
      "name": "Planisfy Streets Light v1",
      "status": "fixture",
      "style": "styles/planisfy-streets-light-v1.json",
      "tileset": "planisfy-streets-v1",
      "schema": "schemas/planisfy-streets-v1.schema.json",
      "center": [9.1829, 48.7758]
    },
    {
      "id": "planisfy-streets-dark-v1",
      "name": "Planisfy Streets Dark v1",
      "status": "fixture",
      "style": "styles/planisfy-streets-dark-v1.json",
      "tileset": "planisfy-streets-v1",
      "schema": "schemas/planisfy-streets-v1.schema.json",
      "center": [9.1829, 48.7758]
    }
  ],
  "glyphs": {
    "defaultUrl": "https://demotiles.maplibre.org/font"
  },
  "sprites": {
    "status": "placeholder",
    "path": "sprites/"
  }
}
